{
  "generated_at": "2026-07-11T14:00:54.514Z",
  "timezone": "UTC",
  "config": {
    "min_event_atom": 1,
    "horizons_hours": [
      1,
      4,
      24,
      168
    ],
    "baseline_lookback_days": 30,
    "event_window_days": 30,
    "price_source": "Kraken OHLC 1h",
    "excluded_delegators": {
      "icf": [
        "cosmos1sufkm72dw7ua9crpfhhp0dqpyuggtlhdse98e7",
        "cosmos1z6czaavlk6kjd48rpf58kqqw9ssad2uaxnazgl"
      ]
    }
  },
  "data_quality": {
    "events_total": 24,
    "exact_timestamp_count": 19,
    "estimated_timestamp_count": 5,
    "exact_timestamp_pct": 0.7916666666666666,
    "candle_count": 721,
    "candle_start": "2026-06-11T14:00:00.000Z",
    "candle_end": "2026-07-11T14:00:00.000Z"
  },
  "recent_bias": {
    "window": "7d",
    "delegation_atom": 0,
    "undelegation_started_atom": 0,
    "undelegation_completed_atom": 0,
    "net_atom": 0,
    "bias_score": 0,
    "bias_label": "Balanced"
  },
  "historical_edge": {
    "delegation": {
      "events": 0,
      "exact_timestamps": 0,
      "estimated_timestamps": 0,
      "horizons": {
        "h1": {
          "count": 0,
          "win_rate": null,
          "median_return": null,
          "median_alpha": null,
          "median_z": null
        },
        "h4": {
          "count": 0,
          "win_rate": null,
          "median_return": null,
          "median_alpha": null,
          "median_z": null
        },
        "h24": {
          "count": 0,
          "win_rate": null,
          "median_return": null,
          "median_alpha": null,
          "median_z": null
        },
        "h168": {
          "count": 0,
          "win_rate": null,
          "median_return": null,
          "median_alpha": null,
          "median_z": null
        }
      }
    },
    "undelegation_initiated": {
      "events": 0,
      "exact_timestamps": 0,
      "estimated_timestamps": 0,
      "horizons": {
        "h1": {
          "count": 0,
          "win_rate": null,
          "median_return": null,
          "median_alpha": null,
          "median_z": null
        },
        "h4": {
          "count": 0,
          "win_rate": null,
          "median_return": null,
          "median_alpha": null,
          "median_z": null
        },
        "h24": {
          "count": 0,
          "win_rate": null,
          "median_return": null,
          "median_alpha": null,
          "median_z": null
        },
        "h168": {
          "count": 0,
          "win_rate": null,
          "median_return": null,
          "median_alpha": null,
          "median_z": null
        }
      }
    },
    "undelegation_completed": {
      "events": 19,
      "exact_timestamps": 19,
      "estimated_timestamps": 0,
      "horizons": {
        "h1": {
          "count": 19,
          "win_rate": 0.47368421052631576,
          "median_return": -0.0009405568096313432,
          "median_alpha": -0.00044416973062472935,
          "median_z": -0.0588369426710425
        },
        "h4": {
          "count": 19,
          "win_rate": 0.3684210526315789,
          "median_return": -0.003248004404073801,
          "median_alpha": -0.0015231038376234147,
          "median_z": -0.11590331148927224
        },
        "h24": {
          "count": 19,
          "win_rate": 0.42105263157894735,
          "median_return": -0.0043717924348983805,
          "median_alpha": 0.009601896737630356,
          "median_z": 0.35858199388427786
        },
        "h168": {
          "count": 19,
          "win_rate": 0.15789473684210525,
          "median_return": -0.10405382290894583,
          "median_alpha": 0.0017969683948226012,
          "median_z": 0.07678407498644414
        }
      }
    }
  },
  "historical_edge_all": {
    "delegation": {
      "events": 0,
      "exact_timestamps": 0,
      "estimated_timestamps": 0,
      "horizons": {
        "h1": {
          "count": 0,
          "win_rate": null,
          "median_return": null,
          "median_alpha": null,
          "median_z": null
        },
        "h4": {
          "count": 0,
          "win_rate": null,
          "median_return": null,
          "median_alpha": null,
          "median_z": null
        },
        "h24": {
          "count": 0,
          "win_rate": null,
          "median_return": null,
          "median_alpha": null,
          "median_z": null
        },
        "h168": {
          "count": 0,
          "win_rate": null,
          "median_return": null,
          "median_alpha": null,
          "median_z": null
        }
      }
    },
    "undelegation_initiated": {
      "events": 0,
      "exact_timestamps": 0,
      "estimated_timestamps": 0,
      "horizons": {
        "h1": {
          "count": 0,
          "win_rate": null,
          "median_return": null,
          "median_alpha": null,
          "median_z": null
        },
        "h4": {
          "count": 0,
          "win_rate": null,
          "median_return": null,
          "median_alpha": null,
          "median_z": null
        },
        "h24": {
          "count": 0,
          "win_rate": null,
          "median_return": null,
          "median_alpha": null,
          "median_z": null
        },
        "h168": {
          "count": 0,
          "win_rate": null,
          "median_return": null,
          "median_alpha": null,
          "median_z": null
        }
      }
    },
    "undelegation_completed": {
      "events": 24,
      "exact_timestamps": 19,
      "estimated_timestamps": 5,
      "horizons": {
        "h1": {
          "count": 24,
          "win_rate": 0.4166666666666667,
          "median_return": -0.0011393648530735323,
          "median_alpha": -0.0007936091366352804,
          "median_z": -0.10585768289072686
        },
        "h4": {
          "count": 24,
          "win_rate": 0.3333333333333333,
          "median_return": -0.0034049007925828767,
          "median_alpha": -0.0025092253230096064,
          "median_z": -0.19990641547957755
        },
        "h24": {
          "count": 24,
          "win_rate": 0.375,
          "median_return": -0.007392333458845768,
          "median_alpha": 0.0033208828838218385,
          "median_z": 0.12416421521738959
        },
        "h168": {
          "count": 24,
          "win_rate": 0.125,
          "median_return": -0.100314171729397,
          "median_alpha": 0.0018870496834546627,
          "median_z": 0.10671120987107963
        }
      }
    }
  },
  "regimes": {
    "delegation": {
      "threshold_vol_24h": null,
      "low_vol": {
        "count": 0,
        "median_edge": null,
        "win_rate": null
      },
      "high_vol": {
        "count": 0,
        "median_edge": null,
        "win_rate": null
      }
    },
    "undelegation_completed": {
      "threshold_vol_24h": 0.006668039802398937,
      "low_vol": {
        "count": 10,
        "median_edge": 0.010871447583769733,
        "win_rate": 0.5
      },
      "high_vol": {
        "count": 9,
        "median_edge": -0.0008426216944242091,
        "win_rate": 0.3333333333333333
      }
    }
  },
  "stability": {
    "delegation_24h": {
      "label": "weak",
      "n": 0,
      "drift": null
    },
    "undelegation_completed_24h": {
      "label": "medium",
      "n": 19,
      "drift": 0.004163830407464253
    }
  },
  "cards": {
    "delegation_24h": {
      "count": 0,
      "edge": null,
      "win_rate": null,
      "confidence": "Low",
      "qualified": false,
      "gate_reason": "No 24h sample yet",
      "mode": "exact_only",
      "window": "24h"
    },
    "undelegation_completed_24h": {
      "count": 19,
      "edge": 0.009601896737630356,
      "win_rate": 0.42105263157894735,
      "confidence": "Medium",
      "qualified": true,
      "gate_reason": "Qualified",
      "mode": "exact_only",
      "window": "24h"
    },
    "flow_24h": {
      "net_atom": 0,
      "delegation_atom": 0,
      "undelegation_atom": 0,
      "total_events": 0,
      "delegation_events": 0,
      "undelegation_events": 0
    },
    "flow_7d": {
      "net_atom": 0,
      "delegation_atom": 0,
      "undelegation_atom": 0,
      "total_events": 0,
      "delegation_events": 0,
      "undelegation_events": 0
    },
    "bias_7d": {
      "label": "Balanced",
      "score": 0,
      "net_atom": 0,
      "text": "0 ATOM net delegation (7d)"
    },
    "quality_gate": {
      "min_samples": 12,
      "min_exact_pct": 0.7
    }
  },
  "events": [
    {
      "category": "undelegation_completed",
      "atom": 71950,
      "timestamp": "2026-06-12T22:22:45.000Z",
      "estimated": false,
      "source": "whale_pending",
      "txhash": "",
      "outcomes": {
        "h1": {
          "return": 0.011466963022832788,
          "alpha": 0.01070222431748852,
          "z": 1.0310662399401427,
          "samples": 33,
          "base_time": 1781305200,
          "future_time": 1781308800
        },
        "h4": {
          "return": 0.009143261264902058,
          "alpha": 0.006740174523037556,
          "z": 0.43437597820912577,
          "samples": 33,
          "base_time": 1781305200,
          "future_time": 1781319600
        },
        "h24": {
          "return": -0.01480096989290769,
          "alpha": -0.01267208848117657,
          "z": -0.9916049542143057,
          "samples": 33,
          "base_time": 1781305200,
          "future_time": 1781391600
        },
        "h168": {
          "return": -0.08607799555465756,
          "alpha": -0.0007014128552759596,
          "z": -0.04402999502981917,
          "samples": 33,
          "base_time": 1781305200,
          "future_time": 1781910000
        }
      }
    },
    {
      "category": "undelegation_completed",
      "atom": 106391,
      "timestamp": "2026-06-13T12:00:00.000Z",
      "estimated": true,
      "source": "pending_schedule_daily",
      "txhash": "",
      "outcomes": {
        "h1": {
          "return": -0.004691993340396494,
          "alpha": -0.0052726870136714605,
          "z": -0.5664860585183595,
          "samples": 46,
          "base_time": 1781352000,
          "future_time": 1781355600
        },
        "h4": {
          "return": -0.007315473487714996,
          "alpha": -0.008128106313232662,
          "z": -0.5887218000677062,
          "samples": 46,
          "base_time": 1781352000,
          "future_time": 1781366400
        },
        "h24": {
          "return": -0.028908733161798095,
          "alpha": -0.02023410878249359,
          "z": -1.322099230507237,
          "samples": 46,
          "base_time": 1781352000,
          "future_time": 1781438400
        },
        "h168": {
          "return": -0.10049947025881645,
          "alpha": -0.01157824642854037,
          "z": -0.7728325283984478,
          "samples": 46,
          "base_time": 1781352000,
          "future_time": 1781956800
        }
      }
    },
    {
      "category": "undelegation_completed",
      "atom": 90128,
      "timestamp": "2026-06-14T12:00:00.000Z",
      "estimated": true,
      "source": "pending_schedule_daily",
      "txhash": "",
      "outcomes": {
        "h1": {
          "return": 0.003273067331670765,
          "alpha": 0.003306974211321531,
          "z": 0.4125613469214193,
          "samples": 70,
          "base_time": 1781438400,
          "future_time": 1781442000
        },
        "h4": {
          "return": 0.02270365752285941,
          "alpha": 0.023209799125795103,
          "z": 1.9727029011317594,
          "samples": 70,
          "base_time": 1781438400,
          "future_time": 1781452800
        },
        "h24": {
          "return": 0.04831670822942624,
          "alpha": 0.04970084556787648,
          "z": 2.645363880639171,
          "samples": 70,
          "base_time": 1781438400,
          "future_time": 1781524800
        },
        "h168": {
          "return": -0.07678719866999173,
          "alpha": 0.0106788093400587,
          "z": 0.811311803224914,
          "samples": 70,
          "base_time": 1781438400,
          "future_time": 1782043200
        }
      }
    },
    {
      "category": "undelegation_completed",
      "atom": 105260,
      "timestamp": "2026-06-15T05:06:58.000Z",
      "estimated": false,
      "source": "whale_pending",
      "txhash": "",
      "outcomes": {
        "h1": {
          "return": -0.008135421930267839,
          "alpha": -0.008429314005546707,
          "z": -1.0732753157126906,
          "samples": 88,
          "base_time": 1781503200,
          "future_time": 1781506800
        },
        "h4": {
          "return": 0.0028297119757452194,
          "alpha": 0.002580310642744923,
          "z": 0.21517429343420855,
          "samples": 88,
          "base_time": 1781503200,
          "future_time": 1781517600
        },
        "h24": {
          "return": -0.007276402223345246,
          "alpha": -0.00543636979517741,
          "z": -0.2780740630570023,
          "samples": 88,
          "base_time": 1781503200,
          "future_time": 1781589600
        },
        "h168": {
          "return": -0.08863062152602319,
          "alpha": 0.001977130972086724,
          "z": 0.13663834475571512,
          "samples": 88,
          "base_time": 1781503200,
          "future_time": 1782108000
        }
      }
    },
    {
      "category": "undelegation_completed",
      "atom": 1724307,
      "timestamp": "2026-06-15T21:03:31.000Z",
      "estimated": false,
      "source": "whale_pending",
      "txhash": "",
      "outcomes": {
        "h1": {
          "return": 0.006761948670662488,
          "alpha": 0.0066422340922045525,
          "z": 0.8757912153965258,
          "samples": 104,
          "base_time": 1781560800,
          "future_time": 1781564400
        },
        "h4": {
          "return": -0.003585881870805774,
          "alpha": -0.0035532721855914434,
          "z": -0.28734978153386004,
          "samples": 104,
          "base_time": 1781560800,
          "future_time": 1781575200
        },
        "h24": {
          "return": 0.021515291224834865,
          "alpha": 0.022164330637224908,
          "z": 1.173586359789424,
          "samples": 104,
          "base_time": 1781560800,
          "future_time": 1781647200
        },
        "h168": {
          "return": -0.0843706777316735,
          "alpha": 0.005648173173925172,
          "z": 0.4165891133478521,
          "samples": 104,
          "base_time": 1781560800,
          "future_time": 1782165600
        }
      }
    },
    {
      "category": "undelegation_completed",
      "atom": 91298,
      "timestamp": "2026-06-15T22:23:35.000Z",
      "estimated": false,
      "source": "whale_pending",
      "txhash": "",
      "outcomes": {
        "h1": {
          "return": -0.006055055207856319,
          "alpha": -0.0062380291586209636,
          "z": -0.8234387928764555,
          "samples": 105,
          "base_time": 1781564400,
          "future_time": 1781568000
        },
        "h4": {
          "return": -0.0035617971810919524,
          "alpha": -0.0034953468083957985,
          "z": -0.28390951946988285,
          "samples": 105,
          "base_time": 1781564400,
          "future_time": 1781578800
        },
        "h24": {
          "return": 0.011703047880730733,
          "alpha": 0.012140998429909108,
          "z": 0.6417457094455723,
          "samples": 105,
          "base_time": 1781564400,
          "future_time": 1781650800
        },
        "h168": {
          "return": -0.08624637459929785,
          "alpha": 0.0037186841808348747,
          "z": 0.27536489864071556,
          "samples": 105,
          "base_time": 1781564400,
          "future_time": 1782169200
        }
      }
    },
    {
      "category": "undelegation_completed",
      "atom": 149862,
      "timestamp": "2026-06-16T12:00:00.000Z",
      "estimated": true,
      "source": "pending_schedule_daily",
      "txhash": "",
      "outcomes": {
        "h1": {
          "return": -0.006983240223463638,
          "alpha": -0.007317154440831759,
          "z": -0.9785090317673291,
          "samples": 118,
          "base_time": 1781611200,
          "future_time": 1781614800
        },
        "h4": {
          "return": -0.008978451715881852,
          "alpha": -0.009514233935959415,
          "z": -0.7689127039653412,
          "samples": 118,
          "base_time": 1781611200,
          "future_time": 1781625600
        },
        "h24": {
          "return": -0.009926177174780393,
          "alpha": -0.010604896265859405,
          "z": -0.5540637965717857,
          "samples": 118,
          "base_time": 1781611200,
          "future_time": 1781697600
        },
        "h168": {
          "return": -0.12330407023144452,
          "alpha": -0.03224419779793232,
          "z": -2.237443642212807,
          "samples": 118,
          "base_time": 1781611200,
          "future_time": 1782216000
        }
      }
    },
    {
      "category": "undelegation_completed",
      "atom": 100000,
      "timestamp": "2026-06-17T02:00:03.000Z",
      "estimated": false,
      "source": "whale_pending",
      "txhash": "",
      "outcomes": {
        "h1": {
          "return": 0.001906290759506435,
          "alpha": 0.0016506502237230618,
          "z": 0.22426012704287904,
          "samples": 133,
          "base_time": 1781665200,
          "future_time": 1781668800
        },
        "h4": {
          "return": -0.0066720176582723,
          "alpha": -0.007221898170393934,
          "z": -0.602936410152321,
          "samples": 133,
          "base_time": 1781665200,
          "future_time": 1781679600
        },
        "h24": {
          "return": -0.06942911608307423,
          "alpha": -0.0667704676128312,
          "z": -3.009979848977273,
          "samples": 133,
          "base_time": 1781665200,
          "future_time": 1781751600
        },
        "h168": {
          "return": -0.14532958763920945,
          "alpha": -0.049400029151253605,
          "z": -2.5335207865052394,
          "samples": 133,
          "base_time": 1781665200,
          "future_time": 1782270000
        }
      }
    },
    {
      "category": "undelegation_completed",
      "atom": 90542,
      "timestamp": "2026-06-18T07:19:40.000Z",
      "estimated": false,
      "source": "whale_pending",
      "txhash": "",
      "outcomes": {
        "h1": {
          "return": 0.0012899758129534256,
          "alpha": 0.0015008951776679935,
          "z": 0.20311394499995303,
          "samples": 162,
          "base_time": 1781769600,
          "future_time": 1781773200
        },
        "h4": {
          "return": -0.012899758129535033,
          "alpha": -0.01145190915622644,
          "z": -0.8756619427562401,
          "samples": 162,
          "base_time": 1781769600,
          "future_time": 1781784000
        },
        "h24": {
          "return": -0.019887127116366643,
          "alpha": -0.0070002793963499284,
          "z": -0.22366247493134747,
          "samples": 162,
          "base_time": 1781769600,
          "future_time": 1781856000
        },
        "h168": {
          "return": -0.11050792797635045,
          "alpha": -0.00582803365014975,
          "z": -0.21050297254307598,
          "samples": 162,
          "base_time": 1781769600,
          "future_time": 1782374400
        }
      }
    },
    {
      "category": "undelegation_completed",
      "atom": 53927,
      "timestamp": "2026-06-18T20:50:08.000Z",
      "estimated": false,
      "source": "whale_pending",
      "txhash": "",
      "outcomes": {
        "h1": {
          "return": 0.0007792496938663351,
          "alpha": 0.0011697297236555005,
          "z": 0.15189053044563516,
          "samples": 175,
          "base_time": 1781816400,
          "future_time": 1781820000
        },
        "h4": {
          "return": 0.011076477791383654,
          "alpha": 0.01290185105972355,
          "z": 0.9756910152627254,
          "samples": 175,
          "base_time": 1781816400,
          "future_time": 1781830800
        },
        "h24": {
          "return": 0.0023377490815985613,
          "alpha": 0.014284801406490704,
          "z": 0.4679810085992666,
          "samples": 175,
          "base_time": 1781816400,
          "future_time": 1781902800
        },
        "h168": {
          "return": -0.10603361905822106,
          "alpha": -0.0006042371269127794,
          "z": -0.02231686343676753,
          "samples": 175,
          "base_time": 1781816400,
          "future_time": 1782421200
        }
      }
    },
    {
      "category": "undelegation_completed",
      "atom": 94002,
      "timestamp": "2026-06-18T22:26:10.000Z",
      "estimated": false,
      "source": "whale_pending",
      "txhash": "",
      "outcomes": {
        "h1": {
          "return": -0.0012701568367572413,
          "alpha": -0.0009287120097253562,
          "z": -0.1209476867591789,
          "samples": 177,
          "base_time": 1781823600,
          "future_time": 1781827200
        },
        "h4": {
          "return": -0.000441793682350311,
          "alpha": 0.0012532415790959925,
          "z": 0.0949024241906484,
          "samples": 177,
          "base_time": 1781823600,
          "future_time": 1781838000
        },
        "h24": {
          "return": -0.0008835873647007331,
          "alpha": 0.010897665946192722,
          "z": 0.35858199388427786,
          "samples": 177,
          "base_time": 1781823600,
          "future_time": 1781910000
        },
        "h168": {
          "return": -0.11105588690081736,
          "alpha": -0.005617630106536098,
          "z": -0.20866245934611802,
          "samples": 177,
          "base_time": 1781823600,
          "future_time": 1782428400
        }
      }
    },
    {
      "category": "undelegation_completed",
      "atom": 3810627,
      "timestamp": "2026-06-18T23:32:02.000Z",
      "estimated": false,
      "source": "whale_pending",
      "txhash": "",
      "outcomes": {
        "h1": {
          "return": 0.004423555432679027,
          "alpha": 0.004770217742911616,
          "z": 0.6229600999829619,
          "samples": 178,
          "base_time": 1781827200,
          "future_time": 1781830800
        },
        "h4": {
          "return": -0.00829416643627312,
          "alpha": -0.006606171857855446,
          "z": -0.5016545545974951,
          "samples": 178,
          "base_time": 1781827200,
          "future_time": 1781841600
        },
        "h24": {
          "return": 0.0001105888858170534,
          "alpha": 0.011830619354316167,
          "z": 0.3902375289925753,
          "samples": 178,
          "base_time": 1781827200,
          "future_time": 1781913600
        },
        "h168": {
          "return": -0.10837710810063583,
          "alpha": -0.0029072915866549254,
          "z": -0.10828044511824457,
          "samples": 178,
          "base_time": 1781827200,
          "future_time": 1782432000
        }
      }
    },
    {
      "category": "undelegation_completed",
      "atom": 1112309,
      "timestamp": "2026-06-19T00:17:27.000Z",
      "estimated": false,
      "source": "whale_pending",
      "txhash": "",
      "outcomes": {
        "h1": {
          "return": -0.0019267822736031004,
          "alpha": -0.0016067692245040955,
          "z": -0.21019470553170586,
          "samples": 179,
          "base_time": 1781830800,
          "future_time": 1781834400
        },
        "h4": {
          "return": -0.003248004404073801,
          "alpha": -0.0015231038376234147,
          "z": -0.11590331148927224,
          "samples": 179,
          "base_time": 1781830800,
          "future_time": 1781845200
        },
        "h24": {
          "return": -0.012496559317368483,
          "alpha": -0.0008426216944242091,
          "z": -0.027860316233549537,
          "samples": 179,
          "base_time": 1781830800,
          "future_time": 1781917200
        },
        "h168": {
          "return": -0.11659785301403802,
          "alpha": -0.01111179464761769,
          "z": -0.41499984944671375,
          "samples": 179,
          "base_time": 1781830800,
          "future_time": 1782435600
        }
      }
    },
    {
      "category": "undelegation_completed",
      "atom": 63000,
      "timestamp": "2026-06-20T10:50:18.000Z",
      "estimated": false,
      "source": "whale_pending",
      "txhash": "",
      "outcomes": {
        "h1": {
          "return": -0.0010085728693898233,
          "alpha": -0.0006585062635452046,
          "z": -0.09076767902227481,
          "samples": 213,
          "base_time": 1781953200,
          "future_time": 1781956800
        },
        "h4": {
          "return": 0.0019611139127024835,
          "alpha": 0.003687882518654494,
          "z": 0.29564316222455633,
          "samples": 213,
          "base_time": 1781953200,
          "future_time": 1781967600
        },
        "h24": {
          "return": -0.007508264694346289,
          "alpha": 0.0038657743398265824,
          "z": 0.13846955444498524,
          "samples": 213,
          "base_time": 1781953200,
          "future_time": 1782039600
        },
        "h168": {
          "return": -0.10012887319997754,
          "alpha": 0.007030212900383817,
          "z": 0.28123837493878884,
          "samples": 213,
          "base_time": 1781953200,
          "future_time": 1782558000
        }
      }
    },
    {
      "category": "undelegation_completed",
      "atom": 62265,
      "timestamp": "2026-06-21T12:01:00.000Z",
      "estimated": false,
      "source": "whale_pending",
      "txhash": "",
      "outcomes": {
        "h1": {
          "return": -0.0021958223073025307,
          "alpha": -0.0018643283478428695,
          "z": -0.2682283425573129,
          "samples": 239,
          "base_time": 1782046800,
          "future_time": 1782050400
        },
        "h4": {
          "return": -0.006643770057992215,
          "alpha": -0.005021510791504626,
          "z": -0.42091496911908,
          "samples": 239,
          "base_time": 1782046800,
          "future_time": 1782061200
        },
        "h24": {
          "return": 0.030009571533134327,
          "alpha": 0.04028357996123062,
          "z": 1.4885989639241186,
          "samples": 239,
          "base_time": 1782046800,
          "future_time": 1782133200
        },
        "h168": {
          "return": -0.11874331400258997,
          "alpha": -0.01050825493759261,
          "z": -0.43708201246692907,
          "samples": 239,
          "base_time": 1782046800,
          "future_time": 1782651600
        }
      }
    },
    {
      "category": "undelegation_completed",
      "atom": 61099,
      "timestamp": "2026-06-21T22:29:35.000Z",
      "estimated": false,
      "source": "whale_pending",
      "txhash": "",
      "outcomes": {
        "h1": {
          "return": 0.01083300074120519,
          "alpha": 0.011201547046391543,
          "z": 1.6402613789590126,
          "samples": 249,
          "base_time": 1782082800,
          "future_time": 1782086400
        },
        "h4": {
          "return": 0.013341695649695007,
          "alpha": 0.014902519732159374,
          "z": 1.2665166666201537,
          "samples": 249,
          "base_time": 1782082800,
          "future_time": 1782097200
        },
        "h24": {
          "return": 0.0238896174240264,
          "alpha": 0.03298813987182849,
          "z": 1.2148320566247328,
          "samples": 249,
          "base_time": 1782082800,
          "future_time": 1782169200
        },
        "h168": {
          "return": -0.10405382290894583,
          "alpha": 0.004377693450895337,
          "z": 0.18564969520412486,
          "samples": 249,
          "base_time": 1782082800,
          "future_time": 1782687600
        }
      }
    },
    {
      "category": "undelegation_completed",
      "atom": 100000,
      "timestamp": "2026-06-22T02:00:02.000Z",
      "estimated": false,
      "source": "whale_pending",
      "txhash": "",
      "outcomes": {
        "h1": {
          "return": 0.010634107916502433,
          "alpha": 0.010944166105413293,
          "z": 1.6050599136912957,
          "samples": 253,
          "base_time": 1782097200,
          "future_time": 1782100800
        },
        "h4": {
          "return": 0.012940977887807348,
          "alpha": 0.014271844517193301,
          "z": 1.2080835703452042,
          "samples": 253,
          "base_time": 1782097200,
          "future_time": 1782111600
        },
        "h24": {
          "return": 0.005401451640128174,
          "alpha": 0.014148855670864756,
          "z": 0.5221681140934895,
          "samples": 253,
          "base_time": 1782097200,
          "future_time": 1782183600
        },
        "h168": {
          "return": -0.10667866989253372,
          "alpha": 0.0017969683948226012,
          "z": 0.07678407498644414,
          "samples": 253,
          "base_time": 1782097200,
          "future_time": 1782702000
        }
      }
    },
    {
      "category": "undelegation_completed",
      "atom": 200000,
      "timestamp": "2026-06-23T02:00:02.000Z",
      "estimated": false,
      "source": "whale_pending",
      "txhash": "",
      "outcomes": {
        "h1": {
          "return": -0.003693547484470261,
          "alpha": -0.003430889907775425,
          "z": -0.5133638637245962,
          "samples": 277,
          "base_time": 1782183600,
          "future_time": 1782187200
        },
        "h4": {
          "return": -0.013543007443057808,
          "alpha": -0.012165760818213873,
          "z": -1.043914735679673,
          "samples": 277,
          "base_time": 1782183600,
          "future_time": 1782198000
        },
        "h24": {
          "return": -0.0465610834405954,
          "alpha": -0.03562676322961225,
          "z": -1.3149854731509374,
          "samples": 277,
          "base_time": 1782183600,
          "future_time": 1782270000
        },
        "h168": {
          "return": -0.14970059880239517,
          "alpha": -0.038272519907395955,
          "z": -1.5533602805430562,
          "samples": 277,
          "base_time": 1782183600,
          "future_time": 1782788400
        }
      }
    },
    {
      "category": "undelegation_completed",
      "atom": 169938,
      "timestamp": "2026-06-24T22:31:02.000Z",
      "estimated": false,
      "source": "whale_pending",
      "txhash": "",
      "outcomes": {
        "h1": {
          "return": -0.006550615636562229,
          "alpha": -0.006076444937286308,
          "z": -0.9072881365597988,
          "samples": 321,
          "base_time": 1782342000,
          "future_time": 1782345600
        },
        "h4": {
          "return": -0.002911384727361077,
          "alpha": -0.0007773949291661709,
          "z": -0.06522122630254114,
          "samples": 321,
          "base_time": 1782342000,
          "future_time": 1782356400
        },
        "h24": {
          "return": -0.023655000909807766,
          "alpha": -0.009117879723517528,
          "z": -0.33105454408710316,
          "samples": 321,
          "base_time": 1782342000,
          "future_time": 1782428400
        },
        "h168": {
          "return": -0.06593073330502819,
          "alpha": 0.044871368762082975,
          "z": 1.738338275771559,
          "samples": 321,
          "base_time": 1782342000,
          "future_time": 1782946800
        }
      }
    },
    {
      "category": "undelegation_completed",
      "atom": 60786,
      "timestamp": "2026-06-25T12:01:00.000Z",
      "estimated": false,
      "source": "whale_pending",
      "txhash": "",
      "outcomes": {
        "h1": {
          "return": 0.027702440914374238,
          "alpha": 0.02834035434773781,
          "z": 4.029311328700206,
          "samples": 335,
          "base_time": 1782392400,
          "future_time": 1782396000
        },
        "h4": {
          "return": 0.03919669378793755,
          "alpha": 0.04161982168600093,
          "z": 3.3217751183054025,
          "samples": 335,
          "base_time": 1782392400,
          "future_time": 1782406800
        },
        "h24": {
          "return": 0.045072969133410856,
          "alpha": 0.05994708813341409,
          "z": 2.2151134378751722,
          "samples": 335,
          "base_time": 1782392400,
          "future_time": 1782478800
        },
        "h168": {
          "return": 0.013108614232209659,
          "alpha": 0.12169291788053865,
          "z": 4.42165258652749,
          "samples": 335,
          "base_time": 1782392400,
          "future_time": 1782997200
        }
      }
    },
    {
      "category": "undelegation_completed",
      "atom": 96244,
      "timestamp": "2026-06-26T20:00:58.000Z",
      "estimated": false,
      "source": "whale_pending",
      "txhash": "",
      "outcomes": {
        "h1": {
          "return": -0.0009405568096313432,
          "alpha": -0.00044416973062472935,
          "z": -0.0588369426710425,
          "samples": 367,
          "base_time": 1782507600,
          "future_time": 1782511200
        },
        "h4": {
          "return": -0.010722347629796736,
          "alpha": -0.008528545551846489,
          "z": -0.6801074815784672,
          "samples": 367,
          "base_time": 1782507600,
          "future_time": 1782522000
        },
        "h24": {
          "return": -0.017995986957612176,
          "alpha": -0.003914787991458011,
          "z": -0.1488736539037659,
          "samples": 367,
          "base_time": 1782507600,
          "future_time": 1782594000
        },
        "h168": {
          "return": 0.006019563581640464,
          "alpha": 0.10673697929302121,
          "z": 2.8889488036181032,
          "samples": 367,
          "base_time": 1782507600,
          "future_time": 1783112400
        }
      }
    },
    {
      "category": "undelegation_completed",
      "atom": 141009,
      "timestamp": "2026-06-27T22:33:42.000Z",
      "estimated": false,
      "source": "whale_pending",
      "txhash": "",
      "outcomes": {
        "h1": {
          "return": -0.0031679655325350664,
          "alpha": -0.0026789533975974293,
          "z": -0.360540243730746,
          "samples": 393,
          "base_time": 1782601200,
          "future_time": 1782604800
        },
        "h4": {
          "return": -0.005829056579864433,
          "alpha": -0.0036532742748383697,
          "z": -0.29535175336609876,
          "samples": 393,
          "base_time": 1782601200,
          "future_time": 1782615600
        },
        "h24": {
          "return": -0.0043717924348983805,
          "alpha": 0.009601896737630356,
          "z": 0.37687315622893186,
          "samples": 393,
          "base_time": 1782601200,
          "future_time": 1782687600
        },
        "h168": {
          "return": 0.009187100044351526,
          "alpha": 0.10298947241301905,
          "z": 2.329108649125614,
          "samples": 393,
          "base_time": 1782601200,
          "future_time": 1783206000
        }
      }
    },
    {
      "category": "undelegation_completed",
      "atom": 116364,
      "timestamp": "2026-06-28T12:00:00.000Z",
      "estimated": true,
      "source": "pending_schedule_daily",
      "txhash": "",
      "outcomes": {
        "h1": {
          "return": -0.006726741972331585,
          "alpha": -0.006249716398006989,
          "z": -0.8511627337883654,
          "samples": 406,
          "base_time": 1782648000,
          "future_time": 1782651600
        },
        "h4": {
          "return": -0.002665312856961477,
          "alpha": -0.0005641877704086139,
          "z": -0.046198535788763505,
          "samples": 406,
          "base_time": 1782648000,
          "future_time": 1782662400
        },
        "h24": {
          "return": -0.010661251427846241,
          "alpha": 0.0027759914278170945,
          "z": 0.10985887598979394,
          "samples": 406,
          "base_time": 1782648000,
          "future_time": 1782734400
        },
        "h168": {
          "return": -0.011359309557050445,
          "alpha": 0.07956545182978261,
          "z": 1.7179300499390826,
          "samples": 406,
          "base_time": 1782648000,
          "future_time": 1783252800
        }
      }
    },
    {
      "category": "undelegation_completed",
      "atom": 107734,
      "timestamp": "2026-06-29T12:00:00.000Z",
      "estimated": true,
      "source": "pending_schedule_daily",
      "txhash": "",
      "outcomes": {
        "h1": {
          "return": -0.01500962155227703,
          "alpha": -0.014534927054415954,
          "z": -2.0125743645369853,
          "samples": 430,
          "base_time": 1782734400,
          "future_time": 1782738000
        },
        "h4": {
          "return": -0.021937139191789634,
          "alpha": -0.019787663378488935,
          "z": -1.647310950327329,
          "samples": 430,
          "base_time": 1782734400,
          "future_time": 1782748800
        },
        "h24": {
          "return": -0.031622835150737605,
          "alpha": -0.017287057117067416,
          "z": -0.6937692709055225,
          "samples": 430,
          "base_time": 1782734400,
          "future_time": 1782820800
        },
        "h168": {
          "return": -0.0030147530468248585,
          "alpha": 0.08264624787330765,
          "z": 1.6531722147511747,
          "samples": 430,
          "base_time": 1782734400,
          "future_time": 1783339200
        }
      }
    }
  ]
}