{
  "generated_at": "2026-06-04T22:05:18.150Z",
  "base": "EUR",
  "source": {
    "name": "Frankfurter (ECB-derived fallback)",
    "url": "https://api.frankfurter.app/latest?from=EUR&to=USD,GBP,TRY,JPY,CNY",
    "note": "Used because ECB XML fetch/parse failed on runner",
    "ecb_issue": {
      "error": "ECB missing: USD, GBP, TRY, JPY, CNY",
      "ecb_date": null
    }
  },
  "rates": {
    "EUR": 1,
    "CNY": 7.8848,
    "GBP": 0.8649,
    "JPY": 186.01,
    "TRY": 53.5137,
    "USD": 1.164
  },
  "date": "2026-06-04"
}