{
  "generated_at": "2026-01-23T18:52:09.506Z",
  "base": "EUR",
  "source": {
    "name": "Frankfurter (ECB-derived fallback)",
    "url": "https://api.frankfurter.app/latest?from=EUR&to=USD,GBP,TRY,JPY,CNY",
    "note": "Used because ECB XML fetch/parse failed on runner",
    "ecb_issue": {
      "error": "ECB missing: USD, GBP, TRY, JPY, CNY",
      "ecb_date": null
    }
  },
  "rates": {
    "EUR": 1,
    "CNY": 8.1778,
    "GBP": 0.8681,
    "JPY": 185.71,
    "TRY": 50.908,
    "USD": 1.1742
  },
  "date": "2026-01-23"
}