{
  "generated_at": "2026-02-26T07:07:50.663Z",
  "daily_totals": [
    {
      "date": "2026-02-22",
      "atom": 107938,
      "delegator_count": 54
    },
    {
      "date": "2026-02-23",
      "atom": 974285,
      "delegator_count": 102
    },
    {
      "date": "2026-02-24",
      "atom": 203727,
      "delegator_count": 153
    },
    {
      "date": "2026-02-25",
      "atom": 130965,
      "delegator_count": 136
    },
    {
      "date": "2026-02-26",
      "atom": 688561,
      "delegator_count": 409
    },
    {
      "date": "2026-02-27",
      "atom": 784657,
      "delegator_count": 298
    },
    {
      "date": "2026-02-28",
      "atom": 135002,
      "delegator_count": 214
    },
    {
      "date": "2026-03-01",
      "atom": 149274,
      "delegator_count": 219
    },
    {
      "date": "2026-03-02",
      "atom": 276122,
      "delegator_count": 210
    },
    {
      "date": "2026-03-03",
      "atom": 207088,
      "delegator_count": 248
    },
    {
      "date": "2026-03-04",
      "atom": 193149,
      "delegator_count": 191
    },
    {
      "date": "2026-03-05",
      "atom": 763700,
      "delegator_count": 224
    },
    {
      "date": "2026-03-06",
      "atom": 296727,
      "delegator_count": 155
    },
    {
      "date": "2026-03-07",
      "atom": 488998,
      "delegator_count": 176
    },
    {
      "date": "2026-03-08",
      "atom": 406560,
      "delegator_count": 171
    },
    {
      "date": "2026-03-09",
      "atom": 138499,
      "delegator_count": 195
    },
    {
      "date": "2026-03-10",
      "atom": 215251,
      "delegator_count": 211
    },
    {
      "date": "2026-03-11",
      "atom": 571997,
      "delegator_count": 225
    },
    {
      "date": "2026-03-12",
      "atom": 954526,
      "delegator_count": 166
    },
    {
      "date": "2026-03-13",
      "atom": 511406,
      "delegator_count": 360
    },
    {
      "date": "2026-03-14",
      "atom": 264449,
      "delegator_count": 645
    },
    {
      "date": "2026-03-15",
      "atom": 321358,
      "delegator_count": 152
    },
    {
      "date": "2026-03-16",
      "atom": 400000,
      "delegator_count": 337
    },
    {
      "date": "2026-03-17",
      "atom": 8202281,
      "delegator_count": 205
    },
    {
      "date": "2026-03-18",
      "atom": 158445,
      "delegator_count": 310
    },
    {
      "date": "2026-03-19",
      "atom": 3733,
      "delegator_count": 27
    }
  ]
}